LICENSE
README.md
setup.py
sadaa/__init__.py
sadaa/akikiki.py
sadaa/datalist.py
sadaa/moon.py
sadaa/wordstory.py
sadaa.egg-info/PKG-INFO
sadaa.egg-info/SOURCES.txt
sadaa.egg-info/dependency_links.txt
sadaa.egg-info/top_level.txt