Metadata-Version: 2.1
Name: sadaa
Version: 0.2.0
Summary: A package for generating random stories.
Home-page: https://github.com/ishanoshada/sadaa
Author: Ishan Oshada
Author-email: ic31908@gmail.com
License: UNKNOWN
Project-URL: Source, https://github.com/ishanoshada/sadaa
Platform: UNKNOWN
Classifier: Programming Language :: Python :: 3
Classifier: License :: OSI Approved :: MIT License
Classifier: Operating System :: OS Independent
